krl_core/__init__.py
krl_core/__version__.py
krl_core/cache.py
krl_core/config/__init__.py
krl_core/config/manager.py
krl_core/logging/__init__.py
krl_core/logging/formatters.py
krl_core/logging/logger.py
krl_open_core-0.2.1.dist-info/licenses/LICENSE
krl_open_core-0.2.1.dist-info/METADATA
krl_open_core-0.2.1.dist-info/WHEEL
krl_open_core-0.2.1.dist-info/top_level.txt
krl_open_core-0.2.1.dist-info/RECORD
