Metadata-Version: 2.4
Name: krl-open-core
Version: 0.2.1
Summary: Shared foundation utilities for the KR-Labs analytics platform
Author-email: "Quipu Research Labs, LLC" <support@krlabs.dev>
Maintainer-email: KR-Labs Foundation <support@krlabs.dev>
License: MIT
Project-URL: Homepage, https://krlabs.dev
Project-URL: Documentation, https://krl-core.readthedocs.io
Project-URL: Repository, https://github.com/KR-Labs/krl-open-core
Project-URL: Bug Tracker, https://github.com/KR-Labs/krl-open-core/issues
Project-URL: Changelog, https://github.com/KR-Labs/krl-open-core/blob/main/CHANGELOG.md
Keywords: krl,utilities,logging,configuration,caching,api-client
Classifier: Development Status :: 3 - Alpha
Classifier: Intended Audience :: Developers
Classifier: Intended Audience :: Science/Research
Classifier: License :: OSI Approved :: MIT License
Classifier: Operating System :: OS Independent
Classifier: Programming Language :: Python :: 3
Classifier: Programming Language :: Python :: 3.11
Classifier: Topic :: Scientific/Engineering
Classifier: Topic :: Software Development :: Libraries :: Python Modules
Classifier: Typing :: Typed
Requires-Python: >=3.11
License-File: LICENSE
Requires-Dist: pyyaml>=6.0
Requires-Dist: python-json-logger>=2.0.0
Requires-Dist: requests>=2.28.0
Requires-Dist: python-dotenv>=1.0.0
Provides-Extra: redis
Requires-Dist: redis>=4.5.0; extra == "redis"
Provides-Extra: dev
Requires-Dist: black>=23.0.0; extra == "dev"
Requires-Dist: flake8>=6.0.0; extra == "dev"
Requires-Dist: isort>=5.12.0; extra == "dev"
Requires-Dist: mypy>=1.0.0; extra == "dev"
Requires-Dist: pre-commit>=3.0.0; extra == "dev"
Requires-Dist: types-pyyaml; extra == "dev"
Requires-Dist: types-requests; extra == "dev"
Provides-Extra: test
Requires-Dist: pytest>=7.2.0; extra == "test"
Requires-Dist: pytest-cov>=4.0.0; extra == "test"
Requires-Dist: pytest-xdist>=3.0.0; extra == "test"
Requires-Dist: pytest-asyncio>=0.20.0; extra == "test"
Requires-Dist: pytest-benchmark>=4.0.0; extra == "test"
Requires-Dist: coverage[toml]>=7.0.0; extra == "test"
Provides-Extra: docs
Requires-Dist: sphinx>=5.3.0; extra == "docs"
Requires-Dist: sphinx-rtd-theme>=1.2.0; extra == "docs"
Requires-Dist: sphinx-autodoc-typehints>=1.22.0; extra == "docs"
Requires-Dist: myst-parser>=1.0.0; extra == "docs"
Provides-Extra: all
Requires-Dist: krl-core[dev,docs,redis,test]; extra == "all"
Dynamic: license-file
